<?xml version="1.0" encoding="UTF-8"?>
<java version="1.8.0_131" class="java.beans.XMLDecoder">
    <object class="java.util.ArrayList">
        <void method="add">
            <object class="com.motel.model.Room" id="Room0">
                <void property="customerRoomList">
                    <object class="org.hibernate.collection.internal.PersistentBag">
                        <void property="owner">
                            <object idref="Room0"/>
                        </void>
                    </object>
                </void>
                <void property="electricWaterList">
                    <object class="org.hibernate.collection.internal.PersistentBag">
                        <void property="owner">
                            <object idref="Room0"/>
                        </void>
                    </object>
                </void>
                <void property="home">
                    <object class="com.motel.model.Home" id="Home0">
                        <void property="address">
                            <string></string>
                        </void>
                        <void property="billList">
                            <object class="org.hibernate.collection.internal.PersistentBag">
                                <void property="owner">
                                    <object idref="Home0"/>
                                </void>
                            </object>
                        </void>
                        <void property="description">
                            <string></string>
                        </void>
                        <void property="groupUserId">
                            <long>1</long>
                        </void>
                        <void property="homeCode">
                            <string></string>
                        </void>
                        <void property="homeId">
                            <long>1</long>
                        </void>
                        <void property="homeName">
                            <string>Hà Nội</string>
                        </void>
                        <void property="roomList">
                            <object class="org.hibernate.collection.internal.PersistentBag">
                                <void property="owner">
                                    <object idref="Home0"/>
                                </void>
                            </object>
                        </void>
                        <void property="status">
                            <long>1</long>
                        </void>
                    </object>
                </void>
                <void property="homeId">
                    <long>1</long>
                </void>
                <void property="price">
                    <long>1500000</long>
                </void>
                <void property="roomId">
                    <long>1</long>
                </void>
                <void property="roomName">
                    <string>Phòng 101</string>
                </void>
                <void property="status">
                    <long>1</long>
                </void>
            </object>
        </void>
        <void method="add">
            <object class="com.motel.model.Room" id="Room1">
                <void property="customerRoomList">
                    <object class="org.hibernate.collection.internal.PersistentBag">
                        <void property="owner">
                            <object idref="Room1"/>
                        </void>
                    </object>
                </void>
                <void property="electricWaterList">
                    <object class="org.hibernate.collection.internal.PersistentBag">
                        <void property="owner">
                            <object idref="Room1"/>
                        </void>
                    </object>
                </void>
                <void property="home">
                    <object idref="Home0"/>
                </void>
                <void property="homeId">
                    <long>1</long>
                </void>
                <void property="price">
                    <long>200000</long>
                </void>
                <void property="roomId">
                    <long>2</long>
                </void>
                <void property="roomName">
                    <string>Phòng 102</string>
                </void>
                <void property="status">
                    <long>1</long>
                </void>
            </object>
        </void>
        <void method="add">
            <object class="com.motel.model.Room" id="Room2">
                <void property="customerRoomList">
                    <object class="org.hibernate.collection.internal.PersistentBag">
                        <void property="owner">
                            <object idref="Room2"/>
                        </void>
                    </object>
                </void>
                <void property="electricWaterList">
                    <object class="org.hibernate.collection.internal.PersistentBag">
                        <void property="owner">
                            <object idref="Room2"/>
                        </void>
                    </object>
                </void>
                <void property="home">
                    <object idref="Home0"/>
                </void>
                <void property="homeId">
                    <long>1</long>
                </void>
                <void property="price">
                    <long>500000</long>
                </void>
                <void property="roomId">
                    <long>3</long>
                </void>
                <void property="roomName">
                    <string>Phòng 103</string>
                </void>
                <void property="status">
                    <long>1</long>
                </void>
            </object>
        </void>
        <void method="add">
            <object class="com.motel.model.Room" id="Room3">
                <void property="customerRoomList">
                    <object class="org.hibernate.collection.internal.PersistentBag">
                        <void property="owner">
                            <object idref="Room3"/>
                        </void>
                    </object>
                </void>
                <void property="electricWaterList">
                    <object class="org.hibernate.collection.internal.PersistentBag">
                        <void property="owner">
                            <object idref="Room3"/>
                        </void>
                    </object>
                </void>
                <void property="home">
                    <object idref="Home0"/>
                </void>
                <void property="homeId">
                    <long>1</long>
                </void>
                <void property="price">
                    <long>1000000</long>
                </void>
                <void property="roomId">
                    <long>8</long>
                </void>
                <void property="roomName">
                    <string>Phòng 104</string>
                </void>
                <void property="status">
                    <long>1</long>
                </void>
            </object>
        </void>
        <void method="add">
            <object class="com.motel.model.Room" id="Room4">
                <void property="customerRoomList">
                    <object class="org.hibernate.collection.internal.PersistentBag">
                        <void property="owner">
                            <object idref="Room4"/>
                        </void>
                    </object>
                </void>
                <void property="electricWaterList">
                    <object class="org.hibernate.collection.internal.PersistentBag">
                        <void property="owner">
                            <object idref="Room4"/>
                        </void>
                    </object>
                </void>
                <void property="home">
                    <object idref="Home0"/>
                </void>
                <void property="homeId">
                    <long>1</long>
                </void>
                <void property="price">
                    <long>1000000</long>
                </void>
                <void property="roomId">
                    <long>9</long>
                </void>
                <void property="roomName">
                    <string>Phòng 105</string>
                </void>
                <void property="status">
                    <long>1</long>
                </void>
            </object>
        </void>
    </object>
</java>
